README.txt
bootstrap.py
buildout.cfg
setup.cfg
setup.py
docs/HISTORY.txt
src/collective/__init__.py
src/collective.beaker.egg-info/PKG-INFO
src/collective.beaker.egg-info/SOURCES.txt
src/collective.beaker.egg-info/dependency_links.txt
src/collective.beaker.egg-info/entry_points.txt
src/collective.beaker.egg-info/namespace_packages.txt
src/collective.beaker.egg-info/not-zip-safe
src/collective.beaker.egg-info/requires.txt
src/collective.beaker.egg-info/top_level.txt
src/collective/beaker/__init__.py
src/collective/beaker/configure.zcml
src/collective/beaker/interfaces.py
src/collective/beaker/meta.zcml
src/collective/beaker/metaconfigure.py
src/collective/beaker/session.py
src/collective/beaker/testing.py
src/collective/beaker/tests.py