Metadata-Version: 1.0
Name: collective.beaker
Version: 1.0b3dev-r239026
Summary: Beaker integration for Zope and Plone
Home-page: http://pypi.python.org/pypi/collective.beaker
Author: Martin Aspeli
Author-email: optilude@gmail.com
License: BSD
Keywords: beaker zope plone caching sessions
Platform: UNKNOWN
Classifier: Framework :: Plone
Classifier: Programming Language :: Python
Classifier: Topic :: Software Development :: Libraries :: Python Modules
